{
    "NAME":"الاسم",
    "EMAIL":"الايميل",
    "PHNAME": "برجاء ادخال الاسم",
    "PHEMAIL": "برجاء ادخال الايميل",
    "EMAILREQUIRED":"الايميل مطلوب برجاء ادخاله",
    "EMAILEXISTS": "هذا الايميل موجود بالفعل",
    "PASS":"الرقم السرى",
    "PHPASS": "برجاء ادخال الرقم السرى",
    "PASSREQUIRED": "الرقم السرى مطلوب برجاء ادخاله",
    "SIGNUP":"انشاء حساب",
    "LOGIN":"الدخول الى حسابى",
    "NAMEREQUIRED":"الاسم مطلوب برجاء ادخاله",
    "INCORRECTEMAIL-PASS":"الايميل او الرقم السرى غير صحيح"




    


}